LAB-2/full-adder-2/full_adder.v
/*
   Full-Adder
   Structure by data flow
*/

module full_adder 
(
        //Port declaration
            //Inputs            
            input a,
            input b,
            input cin,
            //Outputs
            output s,
            output cout
);
	// Wire (net) declarations (internal to module)
	wire p, g;

    assign p = a ^ b;
    assign g = a & b;

    // Create output logic
    assign s = p ^ cin;
    assign cout = g | (p &cin);
 	
endmodule

LAB-2/full-adder-2/full_adder_tb.v
// Testbench for full adder
 `timescale 1ns / 1ps

module test;
    
    reg a, b, cin; //  UUT inputs
    wire s, cout; // UUT outputs

    full_adder uut(.a(a), .b(b), .cin(cin), .s(s), .cout(cout));
    
    initial begin
        a = 0;
        b = 0;
        cin = 0;
        
        $dumpfile("full_adder_tb.vcd");
        $dumpvars(0, test);

        #10
        cin = 1;
        #10
        b = 1; cin = 0;
        #10
        cin = 1;
        #10
        a = 1; b = 0; cin = 0;
        #10
        cin = 1;
        #10
        b = 1; cin = 0;
        #10
        cin = 1;

        #20 $finish;
    end

endmodule

LAB-2/full-adder-2/full_adder_tb.vcd
$date
	Fri May 13 19:38:05 2022
$end
$version
	Icarus Verilog
$end
$timescale
	1ps
$end
$scope module test $end
$var wire 1 ! s $end
$var wire 1 " cout $end
$var reg 1 # a $end
$var reg 1 $ b $end
$var reg 1 % cin $end
$scope module uut $end
$var wire 1 # a $end
$var wire 1 $ b $end
$var wire 1 % cin $end
$var wire 1 " cout $end
$var wire 1 & g $end
$var wire 1 ' p $end
$var wire 1 ! s $end
$upscope $end
$upscope $end
$enddefinitions $end
#0
$dumpvars
0'
0&
0%
0$
0#
0"
0!
$end
#10000
1!
1%
#20000
1'
0%
1$
#30000
1"
0!
1%
#40000
0"
1!
0%
0$
1#
#50000
1"
0!
1%
#60000
0'
1&
0%
1$
#70000
1!
1%
